[{"url":"http://demos.gsi.dit.upm.es/lmf/resource/LisaWashington","sim":"0.625"},{"url":"http://demos.gsi.dit.upm.es/lmf/resource/DonnaPowell","sim":"0.625"},{"url":"http://demos.gsi.dit.upm.es/lmf/resource/KennethLewis","sim":"0.625"},{"url":"http://demos.gsi.dit.upm.es/lmf/resource/PatriciaButler","sim":"0.625"},{"url":"http://demos.gsi.dit.upm.es/lmf/resource/LauraHill","sim":"0.625"},{"url":"http://demos.gsi.dit.upm.es/lmf/resource/DanielBennet","sim":"0.625"},{"url":"http://demos.gsi.dit.upm.es/lmf/resource/KarenKelly","sim":"0.625"},{"url":"http://demos.gsi.dit.upm.es/lmf/resource/LisaAlexander","sim":"0.625"},{"url":"http://demos.gsi.dit.upm.es/lmf/resource/SharonMartinez","sim":"0.625"},{"url":"http://demos.gsi.dit.upm.es/lmf/resource/LauraHughes","sim":"0.625"},{"url":"http://demos.gsi.dit.upm.es/lmf/resource/KennethHill","sim":"0.625"},{"url":"http://demos.gsi.dit.upm.es/lmf/resource/MichelleDiaz","sim":"0.625"},{"url":"http://demos.gsi.dit.upm.es/lmf/resource/NancyScott","sim":"0.625"},{"url":"http://demos.gsi.dit.upm.es/lmf/resource/BarbaraMartinez","sim":"0.625"},{"url":"http://demos.gsi.dit.upm.es/lmf/resource/SarahRobinson","sim":"0.625"},{"url":"http://demos.gsi.dit.upm.es/lmf/resource/ElizabethStewart","sim":"0.625"},{"url":"http://demos.gsi.dit.upm.es/lmf/resource/SarahMorgan","sim":"0.625"},{"url":"http://demos.gsi.dit.upm.es/lmf/resource/DavidFoster","sim":"0.625"},{"url":"http://demos.gsi.dit.upm.es/lmf/resource/HelenNelson","sim":"0.625"},{"url":"http://demos.gsi.dit.upm.es/lmf/resource/StevenJenkings","sim":"0.625"},{"url":"http://demos.gsi.dit.upm.es/lmf/resource/ChristopherRogers","sim":"0.625"},{"url":"http://demos.gsi.dit.upm.es/lmf/resource/DavidPeterson","sim":"0.625"},{"url":"http://demos.gsi.dit.upm.es/lmf/resource/HelenSimmons","sim":"0.625"},{"url":"http://demos.gsi.dit.upm.es/lmf/resource/NancyColeman","sim":"0.625"},{"url":"http://demos.gsi.dit.upm.es/lmf/resource/JosephHoward","sim":"0.625"},{"url":"http://demos.gsi.dit.upm.es/lmf/resource/MarkGray","sim":"0.625"},{"url":"http://demos.gsi.dit.upm.es/lmf/resource/BrianHarris","sim":"0.625"},{"url":"http://demos.gsi.dit.upm.es/lmf/resource/RichardJames","sim":"0.625"},{"url":"http://demos.gsi.dit.upm.es/lmf/resource/RonaldWood","sim":"0.625"},{"url":"http://demos.gsi.dit.upm.es/lmf/resource/CarolEvans","sim":"0.625"},{"url":"http://demos.gsi.dit.upm.es/lmf/resource/HelenGonzalez","sim":"0.625"},{"url":"http://demos.gsi.dit.upm.es/lmf/resource/LindaSimmons","sim":"0.625"},{"url":"http://demos.gsi.dit.upm.es/lmf/resource/AnthonyColeman","sim":"0.625"},{"url":"http://demos.gsi.dit.upm.es/lmf/resource/RichardEvans","sim":"0.625"},{"url":"http://demos.gsi.dit.upm.es/lmf/resource/CarolRichardson","sim":"0.625"},{"url":"http://demos.gsi.dit.upm.es/lmf/resource/ChristopherMoore","sim":"0.625"},{"url":"http://demos.gsi.dit.upm.es/lmf/resource/AnthonyBrown","sim":"0.625"},{"url":"http://demos.gsi.dit.upm.es/lmf/resource/WilliamLopez","sim":"0.625"},{"url":"http://demos.gsi.dit.upm.es/lmf/resource/KarenCook","sim":"0.625"},{"url":"http://demos.gsi.dit.upm.es/lmf/resource/PaulRodriguez","sim":"0.625"},{"url":"http://demos.gsi.dit.upm.es/lmf/resource/DavidJames","sim":"0.625"},{"url":"http://demos.gsi.dit.upm.es/lmf/resource/SandraWard","sim":"0.625"},{"url":"http://demos.gsi.dit.upm.es/lmf/resource/MargaretClark","sim":"0.625"},{"url":"http://demos.gsi.dit.upm.es/lmf/resource/EdwardLopez","sim":"0.625"},{"url":"http://demos.gsi.dit.upm.es/lmf/resource/JamesSanchez","sim":"0.625"},{"url":"http://demos.gsi.dit.upm.es/lmf/resource/ChristopherWalker","sim":"0.625"},{"url":"http://demos.gsi.dit.upm.es/lmf/resource/MichaelJames","sim":"0.625"},{"url":"http://demos.gsi.dit.upm.es/lmf/resource/ChristopherMiller","sim":"0.625"},{"url":"http://demos.gsi.dit.upm.es/lmf/resource/StevenWright","sim":"0.625"},{"url":"http://demos.gsi.dit.upm.es/lmf/resource/CharlesMorgan","sim":"0.625"},{"url":"http://demos.gsi.dit.upm.es/lmf/resource/MariaGonzalez","sim":"0.625"},{"url":"http://demos.gsi.dit.upm.es/lmf/resource/HelenWashington","sim":"0.625"},{"url":"http://demos.gsi.dit.upm.es/lmf/resource/MichelleMartinez","sim":"0.625"},{"url":"http://demos.gsi.dit.upm.es/lmf/resource/LisaDiaz","sim":"0.625"},{"url":"http://demos.gsi.dit.upm.es/lmf/resource/DonaldYoung","sim":"0.625"},{"url":"http://demos.gsi.dit.upm.es/lmf/resource/AnthonyFoster","sim":"0.625"},{"url":"http://demos.gsi.dit.upm.es/lmf/resource/PatriciaGarcia","sim":"0.625"},{"url":"http://demos.gsi.dit.upm.es/lmf/resource/MariaHill","sim":"0.625"},{"url":"http://demos.gsi.dit.upm.es/lmf/resource/RonaldPrice","sim":"0.606735"},{"url":"http://demos.gsi.dit.upm.es/lmf/resource/SusanHenderson","sim":"0.5"},{"url":"http://demos.gsi.dit.upm.es/lmf/resource/HelenRichardson","sim":"0.5"},{"url":"http://demos.gsi.dit.upm.es/lmf/resource/ElizabethRamirez","sim":"0.5"},{"url":"http://demos.gsi.dit.upm.es/lmf/resource/StevenJohnson","sim":"0.5"},{"url":"http://demos.gsi.dit.upm.es/lmf/resource/JasonLopez","sim":"0.5"},{"url":"http://demos.gsi.dit.upm.es/lmf/resource/WilliamCooper","sim":"0.5"},{"url":"http://demos.gsi.dit.upm.es/lmf/resource/DorothyPerez","sim":"0.5"},{"url":"http://demos.gsi.dit.upm.es/lmf/resource/ElizabethRogers","sim":"0.5"},{"url":"http://demos.gsi.dit.upm.es/lmf/resource/NancyHoward","sim":"0.5"},{"url":"http://demos.gsi.dit.upm.es/lmf/resource/KimberlyPerry","sim":"0.5"},{"url":"http://demos.gsi.dit.upm.es/lmf/resource/NancyFoster","sim":"0.5"},{"url":"http://demos.gsi.dit.upm.es/lmf/resource/RuthPowell","sim":"0.5"},{"url":"http://demos.gsi.dit.upm.es/lmf/resource/SusanPatterson","sim":"0.5"},{"url":"http://demos.gsi.dit.upm.es/lmf/resource/HelenLee","sim":"0.5"},{"url":"http://demos.gsi.dit.upm.es/lmf/resource/SarahAnderson","sim":"0.5"},{"url":"http://demos.gsi.dit.upm.es/lmf/resource/CharlesPhilips","sim":"0.5"},{"url":"http://demos.gsi.dit.upm.es/lmf/resource/MarkDavis","sim":"0.5"},{"url":"http://demos.gsi.dit.upm.es/lmf/resource/NancyGonzalez","sim":"0.5"},{"url":"http://demos.gsi.dit.upm.es/lmf/resource/MargaretPerez","sim":"0.5"},{"url":"http://demos.gsi.dit.upm.es/lmf/resource/NancyParker","sim":"0.5"},{"url":"http://demos.gsi.dit.upm.es/lmf/resource/MaryLee","sim":"0.5"},{"url":"http://demos.gsi.dit.upm.es/lmf/resource/WilliamJohnson","sim":"0.5"},{"url":"http://demos.gsi.dit.upm.es/lmf/resource/JasonLewis","sim":"0.5"},{"url":"http://demos.gsi.dit.upm.es/lmf/resource/AnthonyGreen","sim":"0.5"},{"url":"http://demos.gsi.dit.upm.es/lmf/resource/BarbaraMorris","sim":"0.5"},{"url":"http://demos.gsi.dit.upm.es/lmf/resource/SusanJones","sim":"0.5"},{"url":"http://demos.gsi.dit.upm.es/lmf/resource/JasonReed","sim":"0.5"},{"url":"http://demos.gsi.dit.upm.es/lmf/resource/ThomasAdams","sim":"0.5"},{"url":"http://demos.gsi.dit.upm.es/lmf/resource/EdwardJackson","sim":"0.5"},{"url":"http://demos.gsi.dit.upm.es/lmf/resource/SharonPerez","sim":"0.5"},{"url":"http://demos.gsi.dit.upm.es/lmf/resource/KarenSmith","sim":"0.5"},{"url":"http://demos.gsi.dit.upm.es/lmf/resource/MarkMorris","sim":"0.5"},{"url":"http://demos.gsi.dit.upm.es/lmf/resource/BrianDiaz","sim":"0.5"},{"url":"http://demos.gsi.dit.upm.es/lmf/resource/MariaWalker","sim":"0.5"},{"url":"http://demos.gsi.dit.upm.es/lmf/resource/MarkLopez","sim":"0.5"},{"url":"http://demos.gsi.dit.upm.es/lmf/resource/SharonHughes","sim":"0.5"},{"url":"http://demos.gsi.dit.upm.es/lmf/resource/DonnaAlexander","sim":"0.5"},{"url":"http://demos.gsi.dit.upm.es/lmf/resource/MarkCampbell","sim":"0.5"},{"url":"http://demos.gsi.dit.upm.es/lmf/resource/LindaMurphy","sim":"0.481735"},{"url":"http://demos.gsi.dit.upm.es/lmf/resource/JamesPowell","sim":"0.481735"},{"url":"http://demos.gsi.dit.upm.es/lmf/user/pmoncada","sim":"0.0"}]